django_testmigrate/base.py
django_testmigrate/__init__.py
django_testmigrate/management/__init__.py
django_testmigrate/management/commands/testmigrate.py
django_testmigrate/management/commands/__init__.py
django_testmigrate-0.4.0.dist-info/DESCRIPTION.rst
django_testmigrate-0.4.0.dist-info/RECORD
django_testmigrate-0.4.0.dist-info/metadata.json
django_testmigrate-0.4.0.dist-info/WHEEL
django_testmigrate-0.4.0.dist-info/METADATA
django_testmigrate-0.4.0.dist-info/top_level.txt
