Metadata-Version: 2.0
Name: django-testmigrate
Version: 0.4.0
Summary: Lets you write test functions for your migrations.
Home-page: https://github.com/greyside/django-testmigrate
Author: Seán Hayes
Author-email: sean@seanhayes.name
License: BSD
Download-URL: https://github.com/greyside/django-testmigrate
Keywords: django testmigrate migrations
Platform: UNKNOWN
Classifier: Development Status :: 3 - Alpha
Classifier: Intended Audience :: Developers
Classifier: License :: OSI Approved :: BSD License
Classifier: Programming Language :: Python
Classifier: Topic :: Software Development :: Build Tools
Classifier: Topic :: Software Development :: Libraries
Classifier: Topic :: Software Development :: Libraries :: Python Modules
Requires-Dist: django (>=1.8)
Requires-Dist: six
